projex/__init__.py
projex/__main__.py
projex/cli.py
projex/config.py
projex/generator.py
projex/commands/__init__.py
projex/commands/add.py
projex/commands/deps.py
projex/commands/env.py
projex/commands/validate.py
projex/templates/bottle/README.md
projex/templates/bottle/integration.py
projex/templates/bottle/welcome.html
projex/templates/cherrypy/README.md
projex/templates/cherrypy/integration.py
projex/templates/cherrypy/welcome.html
projex/templates/django/README.md
projex/templates/django/integration.py
projex/templates/django/welcome.html
projex/templates/fastapi/README.md
projex/templates/fastapi/integration.py
projex/templates/fastapi/welcome.html
projex/templates/fastapi/welcome_template.py
projex/templates/flask/README.md
projex/templates/flask/integration.py
projex/templates/flask/welcome.html
projex/templates/pyramid/README.md
projex/templates/pyramid/integration.py
projex/templates/pyramid/welcome.html
projex/templates/sanic/README.md
projex/templates/sanic/integration.py
projex/templates/sanic/welcome.html
projex/templates/tornado/README.md
projex/templates/tornado/integration.py
projex/templates/tornado/welcome.html
projex/utils/__init__.py
projex/utils/cicd.py
projex/utils/codegen.py
projex/utils/deps_utils.py
projex/utils/detector.py
projex/utils/docs_utils.py
projex/utils/env_utils.py
projex/utils/gitignore_utils.py
projex/utils/license_utils.py
projex/utils/makefile_utils.py
projex/utils/quality_tools.py
projex/utils/test_utils.py
projex_cli-4.0.1.dist-info/licenses/LICENSE
tests/__init__.py
tests/test_generator.py
projex_cli-4.0.1.dist-info/METADATA
projex_cli-4.0.1.dist-info/WHEEL
projex_cli-4.0.1.dist-info/entry_points.txt
projex_cli-4.0.1.dist-info/top_level.txt
projex_cli-4.0.1.dist-info/RECORD
