Metadata-Version: 2.4
Name: projex-cli
Version: 4.0.1
Summary: A powerful CLI tool to generate Python project boilerplates
Home-page: https://github.com/ChAbdulWahhab/projex
Author: Ch. Abdul Wahab
Author-email: ch.abdul.wahhab@proton.me
Project-URL: Bug Reports, https://github.com/ChAbdulWahhab/projex/issues
Project-URL: Source, https://github.com/ChAbdulWahhab/projex
Classifier: Development Status :: 5 - Production/Stable
Classifier: Intended Audience :: Developers
Classifier: Topic :: Software Development :: Code Generators
Classifier: License :: OSI Approved :: MIT License
Classifier: Programming Language :: Python :: 3
Classifier: Programming Language :: Python :: 3.8
Classifier: Programming Language :: Python :: 3.9
Classifier: Programming Language :: Python :: 3.10
Classifier: Programming Language :: Python :: 3.11
Classifier: Programming Language :: Python :: 3.12
Requires-Python: >=3.8
License-File: LICENSE
Requires-Dist: click>=8.0.0
Requires-Dist: jinja2>=3.0.0
Requires-Dist: rich>=13.0.0
Requires-Dist: pyyaml>=6.0
Requires-Dist: requests>=2.31.0
Dynamic: author
Dynamic: author-email
Dynamic: classifier
Dynamic: description
Dynamic: description-content-type
Dynamic: home-page
Dynamic: license-file
Dynamic: project-url
Dynamic: requires-dist
Dynamic: requires-python
Dynamic: summary
